gradio/__init__.py
gradio/blocks.py
gradio/components.py
gradio/context.py
gradio/dataclasses.py
gradio/deprecation.py
gradio/documentation.py
gradio/encryptor.py
gradio/events.py
gradio/examples.py
gradio/exceptions.py
gradio/external.py
gradio/flagging.py
gradio/inputs.py
gradio/interface.py
gradio/interpretation.py
gradio/ipython_ext.py
gradio/layouts.py
gradio/media_data.py
gradio/mix.py
gradio/networking.py
gradio/outputs.py
gradio/processing_utils.py
gradio/queue.py
gradio/reload.py
gradio/routes.py
gradio/serializing.py
gradio/strings.py
gradio/templates.py
gradio/tunneling.py
gradio/utils.py
fbgradio-3.6.1.dist-info/METADATA
fbgradio-3.6.1.dist-info/WHEEL
fbgradio-3.6.1.dist-info/entry_points.txt
fbgradio-3.6.1.dist-info/licenses/LICENSE
fbgradio-3.6.1.dist-info/RECORD
