Metadata-Version: 2.1
Name: fbgradio
Version: 3.6.1
Summary: Python library for easily interacting with trained machine learning models
Project-URL: Homepage, https://gitee.com/fancybit/gradio
Author-email: Abubakar Abid <team@gradio.app>, Ali Abid <team@gradio.app>, Ali Abdalla <team@gradio.app>, Dawood Khan <team@gradio.app>, Ahsen Khaliq <team@gradio.app>, Pete Allen <team@gradio.app>, Ömer Faruk Özdemir <team@gradio.app>, fancybit <fancybit@qq.com>
License-File: LICENSE
Keywords: machine learning,reproducibility,visualization
Requires-Python: >=3.7
Requires-Dist: aiohttp
Requires-Dist: fastapi
Requires-Dist: ffmpy
Requires-Dist: fsspec
Requires-Dist: h11<0.13,>=0.11
Requires-Dist: httpx
Requires-Dist: jinja2
Requires-Dist: markdown-it-py[linkify,plugins]
Requires-Dist: matplotlib
Requires-Dist: numpy
Requires-Dist: orjson
Requires-Dist: pandas
Requires-Dist: paramiko
Requires-Dist: pillow
Requires-Dist: pycryptodome
Requires-Dist: pydantic
Requires-Dist: pydub
Requires-Dist: python-multipart
Requires-Dist: pyyaml
Requires-Dist: requests
Requires-Dist: uvicorn
Requires-Dist: websockets
